[
  {
    "categoryName": "Demon Snow Leopard Lesi",
    "categoryDisplayName": "Demon Snow Leopard Lesi",
    "coverImage": "/images/Demon Snow Leopard Lesi/VRChat_2025-04-21_02-27-51.012_2160x3840.png",
    "images": [
      "/images/Demon Snow Leopard Lesi/VRChat_2025-04-21_02-27-51.012_2160x3840.png",
      "/images/Demon Snow Leopard Lesi/VRChat_2025-04-21_02-28-34.217_2160x3840.png"
    ]
  },
  {
    "categoryName": "Demon Tigress Lesi",
    "categoryDisplayName": "Demon Tigress Lesi",
    "coverImage": "/images/Demon Tigress Lesi/a.jpg",
    "images": [
      "/images/Demon Tigress Lesi/a.jpg",
      "/images/Demon Tigress Lesi/GmF0BuPbsAAO8jb.jpg",
      "/images/Demon Tigress Lesi/TerryGoof.jpg",
      "/images/Demon Tigress Lesi/TerryInHeaven2.jpg",
      "/images/Demon Tigress Lesi/TerryOrangeMoon-1.jpg"
    ]
  },
  {
    "categoryName": "Demon Tigress Muru",
    "categoryDisplayName": "Demon Tigress Muru",
    "coverImage": "/images/Demon Tigress Muru/Bwah-2.jpg",
    "images": [
      "/images/Demon Tigress Muru/Bwah-2.jpg",
      "/images/Demon Tigress Muru/FingyNom.jpg",
      "/images/Demon Tigress Muru/New avi.jpg",
      "/images/Demon Tigress Muru/WinterBack-1.jpg"
    ]
  },
  {
    "categoryName": "Muru Puppy Girl",
    "categoryDisplayName": "Muru Puppy Girl",
    "coverImage": "/images/Muru Puppy Girl/VRChat_2024-05-06_00-20-21.959_1920x1080.png",
    "images": [
      "/images/Muru Puppy Girl/VRChat_2024-05-06_00-20-21.959_1920x1080.png",
      "/images/Muru Puppy Girl/VRChat_2024-05-16_01-15-49.743_1920x1080.png"
    ]
  },
  {
    "categoryName": "Red Demon Leopard Muru",
    "categoryDisplayName": "Red Demon Leopard Muru",
    "coverImage": "/images/Red Demon Leopard Muru/a.png",
    "images": [
      "/images/Red Demon Leopard Muru/a.png",
      "/images/Red Demon Leopard Muru/GW5kAcAWcAAoTZX.jpg",
      "/images/Red Demon Leopard Muru/VRChat_2024-08-07_20-22-15.956_1920x1080.png",
      "/images/Red Demon Leopard Muru/VRChat_2024-08-07_21-04-14.419_1080x1920.png",
      "/images/Red Demon Leopard Muru/VRChat_2024-08-07_21-14-01.713_1080x1920.png",
      "/images/Red Demon Leopard Muru/VRChat_2024-08-16_01-05-36.943_1080x1920.png",
      "/images/Red Demon Leopard Muru/VRChat_2024-08-18_03-12-41.176_1920x1080.png",
      "/images/Red Demon Leopard Muru/VRChat_2024-08-18_21-05-03.372_1080x1920.png",
      "/images/Red Demon Leopard Muru/VRChat_2024-08-21_22-43-01.010_1920x1080.png",
      "/images/Red Demon Leopard Muru/VRChat_2024-09-06_01-12-57.538_3840x2160.png",
      "/images/Red Demon Leopard Muru/VRChat_2024-09-06_01-50-14.185_3840x2160.png",
      "/images/Red Demon Leopard Muru/VRChat_2024-10-07_21-50-47.382_3840x2160.png",
      "/images/Red Demon Leopard Muru/VRChat_2024-11-16_21-50-23.418_2160x3840.png",
      "/images/Red Demon Leopard Muru/VRChat_2024-11-16_21-57-24.png"
    ]
  },
  {
    "categoryName": "Rin Puppy Girl",
    "categoryDisplayName": "Rin Puppy Girl",
    "coverImage": "/images/Rin Puppy Girl/test.png",
    "images": [
      "/images/Rin Puppy Girl/test.png",
      "/images/Rin Puppy Girl/VRChat_2024-04-20_21-56-10.817_1440x2560.png",
      "/images/Rin Puppy Girl/VRChat_2024-04-20_21-56-19.675_1440x2560.png"
    ]
  },
  {
    "categoryName": "Snow Leopard Muru",
    "categoryDisplayName": "Snow Leopard Muru",
    "coverImage": "/images/Snow Leopard Muru/a.png",
    "images": [
      "/images/Snow Leopard Muru/a.png",
      "/images/Snow Leopard Muru/VRChat_2024-07-13_23-38-27.759_1440x2560.png",
      "/images/Snow Leopard Muru/VRChat_2024-07-13_23-41-56.796_2560x1440.png",
      "/images/Snow Leopard Muru/VRChat_2024-08-05_21-59-31.717_1920x1080.png",
      "/images/Snow Leopard Muru/VRChat_2024-08-07_20-58-00.406_1920x1080.png"
    ]
  },
  {
    "categoryName": "Succubus Lesi",
    "categoryDisplayName": "Succubus Lesi",
    "coverImage": "/images/Succubus Lesi/VRChat_2025-04-19_20-16-22.362_2160x3840.png",
    "images": [
      "/images/Succubus Lesi/VRChat_2025-04-19_20-16-22.362_2160x3840.png"
    ]
  },
  {
    "categoryName": "Were-Muru",
    "categoryDisplayName": "Were Muru",
    "coverImage": "/images/Were-Muru/VRChat_2024-06-11_21-05-20.869_1920x1080.png",
    "images": [
      "/images/Were-Muru/VRChat_2024-06-11_21-05-20.869_1920x1080.png",
      "/images/Were-Muru/VRChat_2024-06-11_21-06-13.799_1920x1080.png"
    ]
  }
]